{
  "_class": "symbolInstance",
  "booleanOperation": 0,
  "do_objectID": "DABD60DE-25AD-4AA4-898B-DAC2D8490633",
  "exportOptions": {
    "_class": "exportOptions",
    "exportFormats": [
    ],
    "includedLayerIds": [
    ],
    "layerOptions": 0,
    "shouldTrim": false
  },
  "frame": {
    "_class": "rect",
    "constrainProportions": false,
    "height": 32,
    "width": 108,
    "x": 580,
    "y": 0
  },
  "horizontalSpacing": 0,
  "isFixedToViewport": false,
  "isFlippedHorizontal": false,
  "isFlippedVertical": false,
  "isLocked": false,
  "isVisible": true,
  "layerListExpandedType": 0,
  "name": "button/large",
  "nameIsFixed": false,
  "overrideValues": [
    {
      "_class": "overrideValue",
      "overrideName": "E9E86D5B-88E5-4DB7-AAF1-7361431F58C0_symbolID",
      "value": "B3C31AC8-07C5-4EFF-B699-4381B4D3B277"
    },
    {
      "_class": "overrideValue",
      "overrideName": "42830D80-14BC-40D9-80C4-BD60F7655C92_symbolID",
      "value": "A5D6AC92-7FBC-456F-B7A0-3F9B48A30C6C"
    },
    {
      "_class": "overrideValue",
      "overrideName": "BE37F95D-BB09-4ABA-8E59-AA6DF673DDC7_symbolID",
      "value": ""
    },
    {
      "_class": "overrideValue",
      "overrideName": "99742DE4-E1FA-4555-99DF-DA01CD70D458_symbolID",
      "value": ""
    },
    {
      "_class": "overrideValue",
      "overrideName": "0E1A118B-CD31-4620-8255-A54E844A7FB8_stringValue",
      "value": " "
    },
    {
      "_class": "overrideValue",
      "overrideName": "BD550721-1BED-4F33-BEFF-8CA32F87D10E_symbolID",
      "value": "B3C31AC8-07C5-4EFF-B699-4381B4D3B277"
    },
    {
      "_class": "overrideValue",
      "overrideName": "1E0D5122-1615-497C-89DE-2E8CEA531AC0_symbolID",
      "value": ""
    }
  ],
  "resizingConstraint": 63,
  "resizingType": 0,
  "rotation": 0,
  "scale": 1,
  "shouldBreakMaskChain": false,
  "style": {
    "_class": "style",
    "endMarkerType": 0,
    "miterLimit": 10,
    "startMarkerType": 0,
    "windingRule": 1
  },
  "symbolID": "96B55D07-16E0-4E2B-BC23-D1E4016D1048",
  "userInfo": {
    "com.animaapp.stc-sketch-plugin": {
      "kModelPropertiesKey": {
      }
    }
  },
  "verticalSpacing": 0
}